MANIFEST.in
README.rst
requirements.txt
setup.py
test_requirements.txt
adjutant_odoo.egg-info/PKG-INFO
adjutant_odoo.egg-info/SOURCES.txt
adjutant_odoo.egg-info/dependency_links.txt
adjutant_odoo.egg-info/requires.txt
adjutant_odoo.egg-info/top_level.txt
odoo_actions/__init__.py
odoo_actions/models.py
odoo_actions/serializers.py
odoo_actions/utils.py
odoo_actions/odoo_client/__init__.py
odoo_actions/odoo_client/client.py
odoo_actions/odoo_client/common.py
odoo_actions/odoo_client/countries.py
odoo_actions/odoo_client/credits.py
odoo_actions/odoo_client/partners.py
odoo_actions/odoo_client/project_relationships.py
odoo_actions/odoo_client/projects.py
odoo_actions/tests/__init__.py
odoo_actions/tests/test_serializers.py
odoo_actions/tests/test_signup_actions.py
odoo_views/__init__.py
odoo_views/models.py
odoo_views/views.py
odoo_views/tests/__init__.py
odoo_views/tests/test_signup_view.py