Metadata-Version: 1.1
Name: adjutant-odoo
Version: 0.2.0
Summary: A plugin for Adjutant with Odoo actions and views.
Home-page: https://github.com/catalyst/adjutant-odoo
Author: Adrian Turjak
Author-email: adriant@catalyst.net.nz
License: Apache 2.0
Keywords: Odoo erp contacts task adjutant workflow
Platform: UNKNOWN
Classifier: Development Status :: 5 - Production/Stable
Classifier: Intended Audience :: Developers
Classifier: Intended Audience :: System Administrators
Classifier: License :: OSI Approved :: Apache Software License
Classifier: Framework :: Django :: 1.11
Classifier: Programming Language :: Python :: 2.7
